MANIFEST.in
setup.py
recording/__init__.py
recording/end_recording.scpt
recording/linux.py
recording/mac.py
recording/start_recording.scpt
screen_recording.egg-info/PKG-INFO
screen_recording.egg-info/SOURCES.txt
screen_recording.egg-info/dependency_links.txt
screen_recording.egg-info/requires.txt
screen_recording.egg-info/top_level.txt