Metadata-Version: 1.1
Name: screen-recording
Version: 0.0.2
Summary: screen recording
Home-page: https://github.com/livingbio/desktop-recording
Author: Tim Hsu
Author-email: tim.yellow@gmail.com
License: MIT
Platform: mac
Classifier: Development Status :: 5 - Production/Stable
Classifier: Environment :: Console
Classifier: Intended Audience :: Developers
Classifier: License :: OSI Approved :: MIT License
Classifier: Operating System :: OS Independent
Classifier: Programming Language :: Python
Classifier: Topic :: Utilities
Classifier: Topic :: Software Development :: Libraries :: Python Modules
